asyncgltrans/__init__.py
asyncgltrans/adapters.py
asyncgltrans/aiosession.py
asyncgltrans/client.py
asyncgltrans/compat.py
asyncgltrans/constants.py
asyncgltrans/gtoken.py
asyncgltrans/models.py
asyncgltrans/urls.py
asyncgltrans/utils.py
asyncgltrans-0.0.23.data/scripts/translate
asyncgltrans-0.0.23.dist-info/LICENSE
asyncgltrans-0.0.23.dist-info/METADATA
asyncgltrans-0.0.23.dist-info/WHEEL
asyncgltrans-0.0.23.dist-info/top_level.txt
asyncgltrans-0.0.23.dist-info/RECORD
