Metadata-Version: 2.1
Name: asyncgltrans
Version: 0.0.23
Summary: Free Google Translate API for Python. Translates totally free of charge.
Home-page: https://github.com/AleksandrKhliupin/py-async-googletrans
Author: Aleksandr Khliupin
Author-email: kampotsasha6@gmail.com
License: MIT
Requires-Dist: requests
Requires-Dist: aiohttp
Provides-Extra: h2
Requires-Dist: hyper ; extra == 'h2'
